Metadata-Version: 2.1
Name: titulosuagrm
Version: 0.1
Summary: Caso de estudio sobre extraccion de datos generados por javascript.
Home-page: https://github.com/zxvega/consulta-uagrm-titulo
Author: Giovanni Vega
License: MIT
License-File: LICENSE
